slumber/__init__.py
slumber/__init__.pyi
slumber/py.typed
slumber/slumber.cpython-313t-powerpc64le-linux-gnu.so
slumber_python-4.2.0.dist-info/METADATA
slumber_python-4.2.0.dist-info/WHEEL
slumber_python-4.2.0.dist-info/RECORD
