Metadata-Version: 2.4
Name: slumber-python
Version: 4.2.0
Classifier: Programming Language :: Rust
Classifier: Programming Language :: Python :: Implementation :: CPython
Classifier: Programming Language :: Python :: Implementation :: PyPy
Summary: Python bindings for Slumber, the source-based REST/HTTP client
Home-Page: https://slumber.lucaspickering.me
License: MIT
Requires-Python: >=3.10
